odoo_image_fetcher/__init__.py
odoo_image_fetcher-0.1.9.dist-info/licenses/LICENSE
odoo_image_fetcher-0.1.9.dist-info/METADATA
odoo_image_fetcher-0.1.9.dist-info/WHEEL
odoo_image_fetcher-0.1.9.dist-info/top_level.txt
odoo_image_fetcher-0.1.9.dist-info/RECORD
