Metadata-Version: 2.4
Name: odoo-image-fetcher
Version: 0.1.9
Summary: A simple utility to fetch images from Odoo via XML-RPC.
Home-page: https://github.com/cloudtechy/odoo-image-fetcher
Download-URL: https://github.com/cloudtechy/odoo-image-fetcher/archive/refs/tags/v0.1.9.tar.gz
Author: Onyekelu Chukwuebuka
Author-email: conyekelu@yahoo.com
Classifier: Programming Language :: Python :: 3
Classifier: License :: OSI Approved :: MIT License
Classifier: Operating System :: OS Independent
Requires-Python: >=3.7
License-File: LICENSE
Requires-Dist: requests
Requires-Dist: python-dotenv
Requires-Dist: urllib3
Dynamic: author
Dynamic: author-email
Dynamic: classifier
Dynamic: description
Dynamic: description-content-type
Dynamic: download-url
Dynamic: home-page
Dynamic: license-file
Dynamic: requires-dist
Dynamic: requires-python
Dynamic: summary
